poly_bus-0.1.0.dist-info/licenses/LICENSE
transport/__init__.py
transport/i_transport.py
transport/transport_factory.py
transport/in_memory/__init__.py
transport/in_memory/in_memory_transport.py
transport/transaction/__init__.py
transport/transaction/incoming_transaction.py
transport/transaction/outgoing_transaction.py
transport/transaction/transaction.py
transport/transaction/transaction_factory.py
transport/transaction/message/__init__.py
transport/transaction/message/incoming_message.py
transport/transaction/message/message.py
transport/transaction/message/message_info.py
transport/transaction/message/message_type.py
transport/transaction/message/messages.py
transport/transaction/message/outgoing_message.py
transport/transaction/message/handlers/__init__.py
transport/transaction/message/handlers/incoming_handler.py
transport/transaction/message/handlers/outgoing_handler.py
transport/transaction/message/handlers/error/__init__.py
transport/transaction/message/handlers/error/error_handlers.py
transport/transaction/message/handlers/serializers/__init__.py
transport/transaction/message/handlers/serializers/json_handlers.py
poly_bus-0.1.0.dist-info/METADATA
poly_bus-0.1.0.dist-info/WHEEL
poly_bus-0.1.0.dist-info/top_level.txt
poly_bus-0.1.0.dist-info/RECORD
